apimatic_pandasport_sdk-1.0.0.dist-info/licenses/LICENSE
pandascorerestapiforallvideogames/__init__.py
pandascorerestapiforallvideogames/api_helper.py
pandascorerestapiforallvideogames/configuration.py
pandascorerestapiforallvideogames/pandascorerestapiforallvideogames_client.py
pandascorerestapiforallvideogames/controllers/__init__.py
pandascorerestapiforallvideogames/controllers/base_controller.py
pandascorerestapiforallvideogames/controllers/incidents_controller.py
pandascorerestapiforallvideogames/controllers/leagues_controller.py
pandascorerestapiforallvideogames/controllers/matches_controller.py
pandascorerestapiforallvideogames/controllers/players_controller.py
pandascorerestapiforallvideogames/controllers/series_controller.py
pandascorerestapiforallvideogames/controllers/teams_controller.py
pandascorerestapiforallvideogames/controllers/tournaments_controller.py
pandascorerestapiforallvideogames/controllers/videogames_controller.py
pandascorerestapiforallvideogames/exceptions/__init__.py
pandascorerestapiforallvideogames/exceptions/api_exception.py
pandascorerestapiforallvideogames/exceptions/error_4001_exception.py
pandascorerestapiforallvideogames/http/__init__.py
pandascorerestapiforallvideogames/http/http_call_back.py
pandascorerestapiforallvideogames/http/http_method_enum.py
pandascorerestapiforallvideogames/http/http_request.py
pandascorerestapiforallvideogames/http/http_response.py
pandascorerestapiforallvideogames/http/proxy_settings.py
pandascorerestapiforallvideogames/http/auth/__init__.py
pandascorerestapiforallvideogames/http/auth/bearer_token.py
pandascorerestapiforallvideogames/http/auth/query_token.py
pandascorerestapiforallvideogames/models/__init__.py
pandascorerestapiforallvideogames/models/base_league.py
pandascorerestapiforallvideogames/models/base_match.py
pandascorerestapiforallvideogames/models/base_player.py
pandascorerestapiforallvideogames/models/base_serie.py
pandascorerestapiforallvideogames/models/base_team.py
pandascorerestapiforallvideogames/models/base_tournament.py
apimatic_pandasport_sdk-1.0.0.dist-info/METADATA
apimatic_pandasport_sdk-1.0.0.dist-info/WHEEL
apimatic_pandasport_sdk-1.0.0.dist-info/top_level.txt
apimatic_pandasport_sdk-1.0.0.dist-info/RECORD
