Metadata-Version: 2.4
Name: apimatic-pandasport-sdk
Version: 1.0.0
Summary: The Pandasport API is a sports data API that provides real-time and historical information on fixtures, results, teams, players, and statistics across multiple sports. It enables developers to easily integrate rich sports data into applications, dashboards, or betting platforms.
Author-email: Muhammad Hamza Shahzad <muhammad.hamza@apimatic.io>
Project-URL: Documentation, https://docs.apimatic.io/
Requires-Python: >=3.7
License-File: LICENSE
Requires-Dist: apimatic-core>=0.2.22,~=0.2.0
Requires-Dist: apimatic-core-interfaces>=0.1.5,~=0.1.0
Requires-Dist: apimatic-requests-client-adapter>=0.1.8,~=0.1.0
Provides-Extra: testutils
Requires-Dist: pytest>=7.2.2; extra == "testutils"
Dynamic: license-file
